voice2text_deltabot/__init__.py
voice2text_deltabot/__main__.py
voice2text_deltabot/_version.py
voice2text_deltabot/hooks.py
voice2text_deltabot-1.4.0.dist-info/LICENSE.txt
voice2text_deltabot-1.4.0.dist-info/METADATA
voice2text_deltabot-1.4.0.dist-info/WHEEL
voice2text_deltabot-1.4.0.dist-info/entry_points.txt
voice2text_deltabot-1.4.0.dist-info/top_level.txt
voice2text_deltabot-1.4.0.dist-info/RECORD
