Metadata-Version: 2.1
Name: voice2text-deltabot
Version: 1.4.0
Summary: Delta Chat bot to extract text from voice messages
Author-email: adbenitez <adb@merlinux.eu>
Project-URL: Homepage, https://github.com/deltachat-bot/voice2text_deltabot
Keywords: deltachat,bot
Classifier: Development Status :: 4 - Beta
Classifier: Programming Language :: Python
Classifier: License :: OSI Approved :: GNU General Public License v3 or later (GPLv3+)
Requires-Python: >=3.8
License-File: LICENSE.txt
Requires-Dist: deltabot-cli <7.0,>=6.1.0
Requires-Dist: faster-whisper
Provides-Extra: dev
Requires-Dist: black ; extra == 'dev'
Requires-Dist: mypy ; extra == 'dev'
Requires-Dist: isort ; extra == 'dev'
Requires-Dist: pylint ; extra == 'dev'
Requires-Dist: pylama ; extra == 'dev'
Requires-Dist: pytest ; extra == 'dev'
